[{"id":880843496,"user":41524,"account_income":12081809,"account_outcome":2860400,"date":"2023-12-18","income":"2500.0000","outcome":"23750.0000","category":2,"payee":"","merchant":null,"comment":"","instrument_income":11303,"instrument_outcome":4,"price":null,"created":"2023-12-18 12:37:15.274068","changed":"2023-12-18 12:37:15.274068+03","deleted":false,"type_income":"checking","type_outcome":"ccard","direction":0,"inbalance_income":true,"inbalance_outcome":true,"hold":false,"tag_group":null,"tag_groups":null,"payee_inflected":[]},{"id":880822308,"user":41524,"account_income":2860424,"account_outcome":2860424,"date":"2023-12-18","income":"0.0000","outcome":"593.4300","category":0,"payee":"ZABKA Z5771 K.1","merchant":null,"comment":"","instrument_income":4,"instrument_outcome":4,"price":null,"created":"2023-12-18 11:47:59","changed":"2023-12-18 11:55:09.695262+03","deleted":false,"type_income":"ccard","type_outcome":"ccard","direction":-1,"inbalance_income":true,"inbalance_outcome":true,"hold":true,"tag_group":837707,"tag_groups":[26251072],"payee_inflected":[]},{"id":880771968,"user":41524,"account_income":2860424,"account_outcome":2860424,"date":"2023-12-18","income":"0.0000","outcome":"500.0000","category":0,"payee":"\u041c\u0430\u043a\u0441","merchant":5521343,"comment":"","instrument_income":4,"instrument_outcome":4,"price":null,"created":"2023-12-18 10:00:54","changed":"2023-12-18 10:02:16.425804+03","deleted":false,"type_income":"ccard","type_outcome":"ccard","direction":-1,"inbalance_income":true,"inbalance_outcome":true,"hold":true,"tag_group":25389629,"tag_groups":[831077],"payee_inflected":[]},{"id":880660363,"user":41524,"account_income":2860424,"account_outcome":2860424,"date":"2023-12-17","income":"0.0000","outcome":"284.9200","category":0,"payee":"Allegro","merchant":6141326,"comment":"\u041a\u0443\u0442\u044f","instrument_income":4,"instrument_outcome":4,"price":null,"created":"2023-12-18 00:03:27","changed":"2023-12-18 12:22:47.03663+03","deleted":false,"type_income":"ccard","type_outcome":"ccard","direction":-1,"inbalance_income":true,"inbalance_outcome":true,"hold":true,"tag_group":756886,"tag_groups":[756886],"payee_inflected":[]},{"id":880660362,"user":41524,"account_income":2860381,"account_outcome":2860424,"date":"2023-12-17","income":"4296.6800","outcome":"4296.6800","category":2,"payee":"","merchant":null,"comment":"\u041c\u0430\u043a\u0430 \u043d\u0430\u0432\u0443\u0448\u043d\u0438\u043a\u0438","instrument_income":4,"instrument_outcome":4,"price":null,"created":"2023-12-17 23:51:45","changed":"2023-12-18 12:44:55.926728+03","deleted":false,"type_income":"cash","type_outcome":"ccard","direction":0,"inbalance_income":false,"inbalance_outcome":true,"hold":true,"tag_group":null,"tag_groups":null,"payee_inflected":[]},{"id":880644014,"user":41524,"account_income":2860424,"account_outcome":2860424,"date":"2023-12-17","income":"0.0000","outcome":"143.4000","category":0,"payee":"12 Balice Manual (2)","merchant":6248064,"comment":"","instrument_income":4,"instrument_outcome":4,"price":null,"created":"2023-12-17 22:50:10","changed":"2023-12-17 23:06:04.530706+03","deleted":false,"type_income":"ccard","type_outcome":"ccard","direction":-1,"inbalance_income":true,"inbalance_outcome":true,"hold":true,"tag_group":1332755,"tag_groups":[15920422],"payee_inflected":[]},{"id":880624138,"user":41524,"account_income":2860424,"account_outcome":2860424,"date":"2023-12-17","income":"0.0000","outcome":"143.4000","category":0,"payee":"7 Brzeczkowice Manual","merchant":6248066,"comment":"","instrument_income":4,"instrument_outcome":4,"price":null,"created":"2023-12-17 22:18:31","changed":"2023-12-17 22:25:47.035445+03","deleted":false,"type_income":"ccard","type_outcome":"ccard","direction":-1,"inbalance_income":true,"inbalance_outcome":true,"hold":true,"tag_group":1332755,"tag_groups":[15920422],"payee_inflected":[]},{"id":880575196,"user":41524,"account_income":2860424,"account_outcome":2860424,"date":"2023-12-17","income":"0.0000","outcome":"1909.8400","category":0,"payee":"Shell","merchant":5485469,"comment":"","instrument_income":4,"instrument_outcome":4,"price":null,"created":"2023-12-17 20:07:16","changed":"2023-12-17 20:25:18.144148+03","deleted":false,"type_income":"ccard","type_outcome":"ccard","direction":-1,"inbalance_income":true,"inbalance_outcome":true,"hold":true,"tag_group":1332755,"tag_groups":[15920422],"payee_inflected":[]},{"id":880521280,"user":41524,"account_income":2860424,"account_outcome":2860424,"date":"2023-12-17","income":"0.0000","outcome":"1588.6000","category":0,"payee":"RESTAURACJA WROCLAWSKA","merchant":6248068,"comment":"","instrument_income":4,"instrument_outcome":4,"price":null,"created":"2023-12-17 18:37:40","changed":"2023-12-17 18:38:17.94345+03","deleted":false,"type_income":"ccard","type_outcome":"ccard","direction":-1,"inbalance_income":true,"inbalance_outcome":true,"hold":true,"tag_group":1332755,"tag_groups":[15920425],"payee_inflected":[]},{"id":880466991,"user":41524,"account_income":2860424,"account_outcome":2860424,"date":"2023-12-17","income":"0.0000","outcome":"114.9400","category":0,"payee":"GW COIN","merchant":6248070,"comment":"","instrument_income":4,"instrument_outcome":4,"price":null,"created":"2023-12-17 16:30:15","changed":"2023-12-17 16:48:26.460353+03","deleted":false,"type_income":"ccard","type_outcome":"ccard","direction":-1,"inbalance_income":true,"inbalance_outcome":true,"hold":true,"tag_group":1332755,"tag_groups":[15920427],"payee_inflected":[]},{"id":880456997,"user":41524,"account_income":2860424,"account_outcome":2860424,"date":"2023-12-17","income":"0.0000","outcome":"181.9600","category":0,"payee":"LWIA BRAMA2 No.2","merchant":6248072,"comment":"","instrument_income":4,"instrument_outcome":4,"price":null,"created":"2023-12-17 16:18:36","changed":"2023-12-17 16:28:01.389712+03","deleted":false,"type_income":"ccard","type_outcome":"ccard","direction":-1,"inbalance_income":true,"inbalance_outcome":true,"hold":true,"tag_group":1332755,"tag_groups":[15920425],"payee_inflected":[]},{"id":880388803,"user":41524,"account_income":2860424,"account_outcome":2860424,"date":"2023-12-17","income":"0.0000","outcome":"143.4000","category":0,"payee":"14 Brzeczkowice Manual","merchant":6248073,"comment":"","instrument_income":4,"instrument_outcome":4,"price":null,"created":"2023-12-17 13:29:04","changed":"2023-12-17 13:46:13.737974+03","deleted":false,"type_income":"ccard","type_outcome":"ccard","direction":-1,"inbalance_income":true,"inbalance_outcome":true,"hold":true,"tag_group":1332755,"tag_groups":[15920422],"payee_inflected":[]},{"id":880368618,"user":41524,"account_income":2860424,"account_outcome":2860424,"date":"2023-12-17","income":"0.0000","outcome":"143.4000","category":0,"payee":"6 Balice Manual (2)","merchant":6248074,"comment":"","instrument_income":4,"instrument_outcome":4,"price":null,"created":"2023-12-17 13:01:37","changed":"2023-12-17 13:06:02.248193+03","deleted":false,"type_income":"ccard","type_outcome":"ccard","direction":-1,"inbalance_income":true,"inbalance_outcome":true,"hold":true,"tag_group":1332755,"tag_groups":[15920422],"payee_inflected":[]},{"id":880835496,"user":41524,"account_income":2860400,"account_outcome":2860400,"date":"2023-12-16","income":"0.0000","outcome":"1501.2200","category":0,"payee":"","merchant":null,"comment":"","instrument_income":4,"instrument_outcome":4,"price":null,"created":"2023-12-18 12:21:40.664895","changed":"2023-12-18 12:21:40.664895+03","deleted":false,"type_income":"ccard","type_outcome":"ccard","direction":-1,"inbalance_income":true,"inbalance_outcome":true,"hold":null,"tag_group":837707,"tag_groups":[2132066],"payee_inflected":[]},{"id":880855368,"user":41524,"account_income":2860400,"account_outcome":2860400,"date":"2023-12-16","income":"0.0000","outcome":"684.0000","category":0,"payee":"","merchant":null,"comment":"\u041f\u043e\u0440\u043e\u0448\u043e\u043a","instrument_income":4,"instrument_outcome":4,"price":null,"created":"2023-12-18 12:20:52","changed":"2023-12-18 12:54:52.167374+03","deleted":false,"type_income":"ccard","type_outcome":"ccard","direction":-1,"inbalance_income":true,"inbalance_outcome":true,"hold":null,"tag_group":756886,"tag_groups":[837711],"payee_inflected":[]},{"id":880855367,"user":41524,"account_income":2860400,"account_outcome":2860400,"date":"2023-12-16","income":"0.0000","outcome":"11275.0100","category":0,"payee":"","merchant":null,"comment":"","instrument_income":4,"instrument_outcome":4,"price":null,"created":"2023-12-18 12:20:51","changed":"2023-12-18 12:54:52.167374+03","deleted":false,"type_income":"ccard","type_outcome":"ccard","direction":-1,"inbalance_income":true,"inbalance_outcome":true,"hold":null,"tag_group":756886,"tag_groups":[756886],"payee_inflected":[]},{"id":880303866,"user":41524,"account_income":12199384,"account_outcome":12199384,"date":"2023-12-16","income":"0.0000","outcome":"90.0000","category":0,"payee":"\u0424\u041e\u041f \u041a\u043e\u0437\u0435\u0440\u043e\u0432\u0430 \u041a\u0430\u0442\u0435\u0440\u0438\u043d\u0430 \u0412\u043e\u043b\u043e\u0434\u0438\u043c\u0438\u0440\u0456\u0432\u043d\u0430","merchant":null,"comment":"","instrument_income":4,"instrument_outcome":4,"price":null,"created":"2023-12-17 01:59:34","changed":"2023-12-17 10:55:14.653535+03","deleted":false,"type_income":"ccard","type_outcome":"ccard","direction":-1,"inbalance_income":true,"inbalance_outcome":true,"hold":true,"tag_group":null,"tag_groups":null,"payee_inflected":[]},{"id":880303867,"user":41524,"account_income":12199384,"account_outcome":12199384,"date":"2023-12-16","income":"0.0000","outcome":"3417.5700","category":0,"payee":"Victoria\u2019s Secret","merchant":6248054,"comment":"","instrument_income":4,"instrument_outcome":4,"price":null,"created":"2023-12-17 01:55:49","changed":"2023-12-17 10:55:14.653535+03","deleted":false,"type_income":"ccard","type_outcome":"ccard","direction":-1,"inbalance_income":true,"inbalance_outcome":true,"hold":true,"tag_group":756897,"tag_groups":[756897],"payee_inflected":[]},{"id":880186733,"user":41524,"account_income":2860424,"account_outcome":2860424,"date":"2023-12-16","income":"0.0000","outcome":"210.4200","category":0,"payee":"BEER STREET","merchant":6090634,"comment":"","instrument_income":4,"instrument_outcome":4,"price":null,"created":"2023-12-17 00:07:47","changed":"2023-12-17 16:28:01.389712+03","deleted":false,"type_income":"ccard","type_outcome":"ccard","direction":-1,"inbalance_income":true,"inbalance_outcome":true,"hold":false,"tag_group":837707,"tag_groups":[31707092],"payee_inflected":[]},{"id":880183726,"user":41524,"account_income":2860424,"account_outcome":2860424,"date":"2023-12-16","income":"0.0000","outcome":"740.0000","category":0,"payee":"\u0404\u0432\u0433\u0435\u043d \u0414.","merchant":6248055,"comment":"","instrument_income":4,"instrument_outcome":4,"price":null,"created":"2023-12-16 23:43:58","changed":"2023-12-18 12:52:24.783141+03","deleted":false,"type_income":"ccard","type_outcome":"ccard","direction":-1,"inbalance_income":true,"inbalance_outcome":true,"hold":true,"tag_group":837707,"tag_groups":[31707092],"payee_inflected":[]},{"id":880129937,"user":41524,"account_income":2860424,"account_outcome":2860424,"date":"2023-12-16","income":"0.0000","outcome":"296.5300","category":0,"payee":"ZABKA Z7306 K.1","merchant":6177065,"comment":"","instrument_income":4,"instrument_outcome":4,"price":null,"created":"2023-12-16 21:22:19","changed":"2023-12-17 16:28:01.389712+03","deleted":false,"type_income":"ccard","type_outcome":"ccard","direction":-1,"inbalance_income":true,"inbalance_outcome":true,"hold":false,"tag_group":837707,"tag_groups":[26251072],"payee_inflected":[]},{"id":880079488,"user":41524,"account_income":2860424,"account_outcome":2860424,"date":"2023-12-16","income":"0.0000","outcome":"200.0000","category":0,"payee":"\u041c\u0430\u043a\u0441\u0438\u043c","merchant":4630495,"comment":"","instrument_income":4,"instrument_outcome":4,"price":null,"created":"2023-12-16 19:16:34","changed":"2023-12-16 19:34:10.173524+03","deleted":false,"type_income":"ccard","type_outcome":"ccard","direction":-1,"inbalance_income":true,"inbalance_outcome":true,"hold":true,"tag_group":756886,"tag_groups":[756886],"payee_inflected":[]},{"id":879991030,"user":41524,"account_income":2860424,"account_outcome":2860424,"date":"2023-12-16","income":"0.0000","outcome":"2520.1200","category":0,"payee":"Castorama","merchant":6177254,"comment":"\u042f\u043b\u0438\u043d\u043a\u0430, \u043f\u0456\u0434\u0441\u0442\u0430\u0432\u043a\u0430, \u043a\u043b\u0435\u0439, \u0440\u043e\u0437\u0435\u0442\u043a\u0438, \u0434\u0440\u0456\u0442","instrument_income":4,"instrument_outcome":4,"price":null,"created":"2023-12-16 14:47:11","changed":"2023-12-18 12:27:12.044796+03","deleted":false,"type_income":"ccard","type_outcome":"ccard","direction":-1,"inbalance_income":true,"inbalance_outcome":true,"hold":false,"tag_group":31646942,"tag_groups":[31646942],"payee_inflected":[]},{"id":880303865,"user":41524,"account_income":12199384,"account_outcome":12199384,"date":"2023-12-16","income":"0.0000","outcome":"230.0000","category":0,"payee":"Vodafone\n+380958960823","merchant":null,"comment":"","instrument_income":4,"instrument_outcome":4,"price":null,"created":"2023-12-16 12:41:06","changed":"2023-12-17 10:55:14.653535+03","deleted":false,"type_income":"ccard","type_outcome":"ccard","direction":-1,"inbalance_income":true,"inbalance_outcome":true,"hold":true,"tag_group":842534,"tag_groups":[756895],"payee_inflected":[]},{"id":879848156,"user":41524,"account_income":2860424,"account_outcome":2860424,"date":"2023-12-15","income":"0.0000","outcome":"285.3000","category":0,"payee":"CERASUS SP. Z O.O. SP.","merchant":6159617,"comment":"","instrument_income":4,"instrument_outcome":4,"price":null,"created":"2023-12-16 01:53:51","changed":"2023-12-16 15:54:02.055373+03","deleted":false,"type_income":"ccard","type_outcome":"ccard","direction":-1,"inbalance_income":true,"inbalance_outcome":true,"hold":false,"tag_group":837707,"tag_groups":[33078367],"payee_inflected":[]},{"id":879848155,"user":41524,"account_income":2860424,"account_outcome":2860424,"date":"2023-12-15","income":"0.0000","outcome":"1244.1500","category":0,"payee":"BEER HOUSE PUB RESTO","merchant":2343100,"comment":"","instrument_income":4,"instrument_outcome":4,"price":null,"created":"2023-12-16 01:38:17","changed":"2023-12-16 15:54:02.055373+03","deleted":false,"type_income":"ccard","type_outcome":"ccard","direction":-1,"inbalance_income":true,"inbalance_outcome":true,"hold":false,"tag_group":837707,"tag_groups":[33078367],"payee_inflected":[]},{"id":879749859,"user":41524,"account_income":2860424,"account_outcome":2860424,"date":"2023-12-15","income":"0.0000","outcome":"285.3000","category":0,"payee":"CERASUS SP. Z O.O. SP.","merchant":6159617,"comment":"","instrument_income":4,"instrument_outcome":4,"price":null,"created":"2023-12-15 23:33:37","changed":"2023-12-16 15:54:02.055373+03","deleted":false,"type_income":"ccard","type_outcome":"ccard","direction":-1,"inbalance_income":true,"inbalance_outcome":true,"hold":false,"tag_group":837707,"tag_groups":[33078367],"payee_inflected":[]},{"id":879551943,"user":41524,"account_income":12199384,"account_outcome":12199384,"date":"2023-12-15","income":"0.0000","outcome":"296.1500","category":0,"payee":"ZABKA Z7306 K.1","merchant":6177065,"comment":"","instrument_income":4,"instrument_outcome":4,"price":null,"created":"2023-12-15 16:01:40","changed":"2023-12-17 10:55:14.653535+03","deleted":false,"type_income":"ccard","type_outcome":"ccard","direction":-1,"inbalance_income":true,"inbalance_outcome":true,"hold":false,"tag_group":837707,"tag_groups":[26251072],"payee_inflected":[]},{"id":879537623,"user":41524,"account_income":12199384,"account_outcome":12199384,"date":"2023-12-15","income":"0.0000","outcome":"384.5100","category":0,"payee":"Lidl","merchant":6090638,"comment":"","instrument_income":4,"instrument_outcome":4,"price":null,"created":"2023-12-15 15:46:22","changed":"2023-12-17 10:55:14.653535+03","deleted":false,"type_income":"ccard","type_outcome":"ccard","direction":-1,"inbalance_income":true,"inbalance_outcome":true,"hold":false,"tag_group":756886,"tag_groups":[756886],"payee_inflected":[]},{"id":879533828,"user":41524,"account_income":2860424,"account_outcome":2860424,"date":"2023-12-15","income":"0.0000","outcome":"587.0700","category":0,"payee":"UPC","merchant":6167367,"comment":"","instrument_income":4,"instrument_outcome":4,"price":null,"created":"2023-12-15 15:28:21","changed":"2023-12-16 15:54:02.055373+03","deleted":false,"type_income":"ccard","type_outcome":"ccard","direction":-1,"inbalance_income":true,"inbalance_outcome":true,"hold":false,"tag_group":842534,"tag_groups":[756895],"payee_inflected":[]},{"id":879508902,"user":41524,"account_income":2860424,"account_outcome":2860424,"date":"2023-12-15","income":"0.0000","outcome":"160.0000","category":0,"payee":"\u041c\u0430\u043a\u0441\u0438\u043c","merchant":4630495,"comment":"","instrument_income":4,"instrument_outcome":4,"price":null,"created":"2023-12-15 14:20:05","changed":"2023-12-18 12:29:43.189451+03","deleted":false,"type_income":"ccard","type_outcome":"ccard","direction":-1,"inbalance_income":true,"inbalance_outcome":true,"hold":true,"tag_group":756886,"tag_groups":[756886],"payee_inflected":[]},{"id":879470825,"user":41524,"account_income":2860424,"account_outcome":2860424,"date":"2023-12-15","income":"0.0000","outcome":"286.4200","category":0,"payee":"ORANGE FLEX","merchant":6090628,"comment":"","instrument_income":4,"instrument_outcome":4,"price":null,"created":"2023-12-15 13:13:04","changed":"2023-12-16 15:54:02.055373+03","deleted":false,"type_income":"ccard","type_outcome":"ccard","direction":-1,"inbalance_income":true,"inbalance_outcome":true,"hold":false,"tag_group":842534,"tag_groups":[756895],"payee_inflected":[]},{"id":879449185,"user":41524,"account_income":2860424,"account_outcome":2860400,"date":"2023-12-15","income":"20000.0000","outcome":"20000.0000","category":2,"payee":"","merchant":null,"comment":"","instrument_income":4,"instrument_outcome":4,"price":null,"created":"2023-12-15 12:35:41","changed":"2023-12-15 12:38:22.427952+03","deleted":false,"type_income":"ccard","type_outcome":"ccard","direction":0,"inbalance_income":true,"inbalance_outcome":true,"hold":true,"tag_group":null,"tag_groups":null,"payee_inflected":[]},{"id":879416795,"user":41524,"account_income":2860424,"account_outcome":2860424,"date":"2023-12-15","income":"0.0000","outcome":"1128.8300","category":0,"payee":"AliExpress","merchant":5113528,"comment":"","instrument_income":4,"instrument_outcome":4,"price":null,"created":"2023-12-15 11:09:00","changed":"2023-12-15 23:40:30.975174+03","deleted":false,"type_income":"ccard","type_outcome":"ccard","direction":-1,"inbalance_income":true,"inbalance_outcome":true,"hold":false,"tag_group":31646942,"tag_groups":[31646943],"payee_inflected":[]},{"id":879393306,"user":41524,"account_income":2860424,"account_outcome":2860424,"date":"2023-12-15","income":"0.0000","outcome":"100.0000","category":0,"payee":"\u041f\u043e\u043f\u043e\u0432\u043d\u0435\u043d\u043d\u044f \u00ab\u041d\u0430 \u041f\u0442\u0430\u0448\u043a\u0438 88 \u043e\u0431\u043c\u043f\u00bb","merchant":null,"comment":"","instrument_income":4,"instrument_outcome":4,"price":null,"created":"2023-12-15 10:10:57","changed":"2023-12-15 12:38:22.427952+03","deleted":false,"type_income":"ccard","type_outcome":"ccard","direction":-1,"inbalance_income":true,"inbalance_outcome":true,"hold":true,"tag_group":842559,"tag_groups":[26669777],"payee_inflected":[]},{"id":879182577,"user":41524,"account_income":2860424,"account_outcome":2860424,"date":"2023-12-14","income":"0.0000","outcome":"468.3800","category":0,"payee":"Jakdojade","merchant":6090639,"comment":"","instrument_income":4,"instrument_outcome":4,"price":null,"created":"2023-12-14 19:52:50","changed":"2023-12-15 14:36:41.091261+03","deleted":false,"type_income":"ccard","type_outcome":"ccard","direction":-1,"inbalance_income":true,"inbalance_outcome":true,"hold":false,"tag_group":7033404,"tag_groups":[34999525],"payee_inflected":[]},{"id":879499856,"user":41524,"account_income":12199384,"account_outcome":12199384,"date":"2023-12-14","income":"0.0000","outcome":"700.0000","category":0,"payee":"\u041c\u0430\u043a\u0441\u0438\u043c\u0447\u0438\u043a","merchant":6248086,"comment":"","instrument_income":4,"instrument_outcome":4,"price":null,"created":"2023-12-14 19:28:28","changed":"2023-12-15 14:21:05.340523+03","deleted":false,"type_income":"ccard","type_outcome":"ccard","direction":-1,"inbalance_income":true,"inbalance_outcome":true,"hold":true,"tag_group":756886,"tag_groups":[756886],"payee_inflected":[]},{"id":879499847,"user":41524,"account_income":12199384,"account_outcome":12199384,"date":"2023-12-14","income":"0.0000","outcome":"1713.2800","category":0,"payee":"AliExpress","merchant":5113528,"comment":"","instrument_income":4,"instrument_outcome":4,"price":null,"created":"2023-12-14 13:20:35","changed":"2023-12-15 14:21:05.340523+03","deleted":false,"type_income":"ccard","type_outcome":"ccard","direction":-1,"inbalance_income":true,"inbalance_outcome":true,"hold":false,"tag_group":null,"tag_groups":null,"payee_inflected":[]},{"id":879499853,"user":41524,"account_income":12199384,"account_outcome":12199384,"date":"2023-12-14","income":"0.0000","outcome":"457.9000","category":0,"payee":"Allegro","merchant":6141326,"comment":"","instrument_income":4,"instrument_outcome":4,"price":null,"created":"2023-12-14 12:40:26","changed":"2023-12-15 14:21:05.340523+03","deleted":false,"type_income":"ccard","type_outcome":"ccard","direction":-1,"inbalance_income":true,"inbalance_outcome":true,"hold":false,"tag_group":null,"tag_groups":null,"payee_inflected":[]},{"id":878960478,"user":41524,"account_income":2860424,"account_outcome":2860424,"date":"2023-12-14","income":"0.0000","outcome":"308.8800","category":0,"payee":"ZABKA Z6280 K.1","merchant":null,"comment":"","instrument_income":4,"instrument_outcome":4,"price":null,"created":"2023-12-14 11:46:16","changed":"2023-12-15 22:52:30.204095+03","deleted":false,"type_income":"ccard","type_outcome":"ccard","direction":-1,"inbalance_income":true,"inbalance_outcome":true,"hold":false,"tag_group":837707,"tag_groups":[26251072],"payee_inflected":[]},{"id":878734275,"user":41524,"account_income":2860424,"account_outcome":2860424,"date":"2023-12-13","income":"0.0000","outcome":"149.3900","category":0,"payee":"MEDIA MARKT P505 K.101","merchant":6134243,"comment":"\u041c\u0456\u043d\u0456\u0434\u0436\u0435\u043a","instrument_income":4,"instrument_outcome":4,"price":null,"created":"2023-12-13 20:04:34","changed":"2023-12-15 12:38:22.427952+03","deleted":false,"type_income":"ccard","type_outcome":"ccard","direction":-1,"inbalance_income":true,"inbalance_outcome":true,"hold":false,"tag_group":31646942,"tag_groups":[31646943],"payee_inflected":[]},{"id":878631362,"user":41524,"account_income":2860424,"account_outcome":2860424,"date":"2023-12-13","income":"0.0000","outcome":"280.4300","category":0,"payee":"BEER HOUSE PUB RESTO","merchant":2343100,"comment":"","instrument_income":4,"instrument_outcome":4,"price":null,"created":"2023-12-13 15:43:13","changed":"2023-12-14 20:13:41.808537+03","deleted":false,"type_income":"ccard","type_outcome":"ccard","direction":-1,"inbalance_income":true,"inbalance_outcome":true,"hold":false,"tag_group":756886,"tag_groups":[7107248],"payee_inflected":[]},{"id":878534982,"user":41524,"account_income":2860424,"account_outcome":2860424,"date":"2023-12-13","income":"0.0000","outcome":"308.1800","category":0,"payee":"ZABKA Z5771 K.1","merchant":null,"comment":"","instrument_income":4,"instrument_outcome":4,"price":null,"created":"2023-12-13 12:01:49","changed":"2023-12-14 20:13:41.808537+03","deleted":false,"type_income":"ccard","type_outcome":"ccard","direction":-1,"inbalance_income":true,"inbalance_outcome":true,"hold":false,"tag_group":837707,"tag_groups":[26251072],"payee_inflected":[]},{"id":878509122,"user":41524,"account_income":2860424,"account_outcome":2860424,"date":"2023-12-13","income":"0.0000","outcome":"100.0000","category":0,"payee":"\u041f\u043e\u043f\u043e\u0432\u043d\u0435\u043d\u043d\u044f \u00ab\u041d\u0430 \u0433\u0432\u0438\u043d\u0442\u0456\u0432\u043a\u0443\u00bb","merchant":null,"comment":"","instrument_income":4,"instrument_outcome":4,"price":null,"created":"2023-12-13 11:38:50","changed":"2023-12-15 12:38:22.427952+03","deleted":false,"type_income":"ccard","type_outcome":"ccard","direction":-1,"inbalance_income":true,"inbalance_outcome":true,"hold":true,"tag_group":842559,"tag_groups":[26669777],"payee_inflected":[]},{"id":879499850,"user":41524,"account_income":12199384,"account_outcome":12199384,"date":"2023-12-12","income":"0.0000","outcome":"242.6400","category":0,"payee":"SERHIIHUPA.COM","merchant":6248088,"comment":"","instrument_income":4,"instrument_outcome":4,"price":null,"created":"2023-12-12 19:20:39","changed":"2023-12-15 14:21:05.340523+03","deleted":false,"type_income":"ccard","type_outcome":"ccard","direction":-1,"inbalance_income":true,"inbalance_outcome":true,"hold":false,"tag_group":756897,"tag_groups":[756897],"payee_inflected":[]},{"id":879499848,"user":41524,"account_income":12199384,"account_outcome":12199384,"date":"2023-12-11","income":"0.0000","outcome":"280.1300","category":0,"payee":"ORANGE FLEX","merchant":6090628,"comment":"","instrument_income":4,"instrument_outcome":4,"price":null,"created":"2023-12-11 20:06:01","changed":"2023-12-15 14:21:05.340523+03","deleted":false,"type_income":"ccard","type_outcome":"ccard","direction":-1,"inbalance_income":true,"inbalance_outcome":true,"hold":false,"tag_group":842534,"tag_groups":[756895],"payee_inflected":[]},{"id":877663285,"user":41524,"account_income":2860424,"account_outcome":2860424,"date":"2023-12-11","income":"0.0000","outcome":"691.1500","category":0,"payee":"APTEKA DR. MAX","merchant":null,"comment":"","instrument_income":4,"instrument_outcome":4,"price":null,"created":"2023-12-11 16:29:59","changed":"2023-12-13 11:40:02.702362+03","deleted":false,"type_income":"ccard","type_outcome":"ccard","direction":-1,"inbalance_income":true,"inbalance_outcome":true,"hold":false,"tag_group":842783,"tag_groups":[837712],"payee_inflected":[]},{"id":877652901,"user":41524,"account_income":2860424,"account_outcome":2860424,"date":"2023-12-11","income":"0.0000","outcome":"354.9300","category":0,"payee":"BEER HOUSE PUB RESTO","merchant":2343100,"comment":"","instrument_income":4,"instrument_outcome":4,"price":null,"created":"2023-12-11 16:13:50","changed":"2023-12-13 11:40:02.702362+03","deleted":false,"type_income":"ccard","type_outcome":"ccard","direction":-1,"inbalance_income":true,"inbalance_outcome":true,"hold":false,"tag_group":756886,"tag_groups":[7107248],"payee_inflected":[]},{"id":877511263,"user":41524,"account_income":2860424,"account_outcome":2860424,"date":"2023-12-11","income":"0.0000","outcome":"308.1800","category":0,"payee":"ZABKA Z5771 K.1","merchant":null,"comment":"","instrument_income":4,"instrument_outcome":4,"price":null,"created":"2023-12-11 11:59:38","changed":"2023-12-13 11:40:02.702362+03","deleted":false,"type_income":"ccard","type_outcome":"ccard","direction":-1,"inbalance_income":true,"inbalance_outcome":true,"hold":false,"tag_group":837707,"tag_groups":[26251072],"payee_inflected":[]},{"id":879499849,"user":41524,"account_income":12199384,"account_outcome":12199384,"date":"2023-12-11","income":"0.0000","outcome":"283.8700","category":0,"payee":"ZABKA Z7306 K.1","merchant":6177065,"comment":"","instrument_income":4,"instrument_outcome":4,"price":null,"created":"2023-12-11 11:34:58","changed":"2023-12-15 14:21:05.340523+03","deleted":false,"type_income":"ccard","type_outcome":"ccard","direction":-1,"inbalance_income":true,"inbalance_outcome":true,"hold":false,"tag_group":837707,"tag_groups":[26251072],"payee_inflected":[]},{"id":877444711,"user":41524,"account_income":2860424,"account_outcome":2860424,"date":"2023-12-11","income":"0.0000","outcome":"200.0000","category":0,"payee":"\u041c\u0430\u043a\u0441\u0438\u043c","merchant":4630495,"comment":"","instrument_income":4,"instrument_outcome":4,"price":null,"created":"2023-12-11 10:03:31","changed":"2023-12-11 10:03:44.805682+03","deleted":false,"type_income":"ccard","type_outcome":"ccard","direction":-1,"inbalance_income":true,"inbalance_outcome":true,"hold":true,"tag_group":25389629,"tag_groups":[831077],"payee_inflected":[]},{"id":877444712,"user":41524,"account_income":2860424,"account_outcome":2860424,"date":"2023-12-11","income":"0.0000","outcome":"300.0000","category":0,"payee":"\u041c\u0430\u043a\u0441\u0438\u043c","merchant":4630495,"comment":"","instrument_income":4,"instrument_outcome":4,"price":null,"created":"2023-12-11 10:00:46","changed":"2023-12-11 10:03:34.927684+03","deleted":false,"type_income":"ccard","type_outcome":"ccard","direction":-1,"inbalance_income":true,"inbalance_outcome":true,"hold":true,"tag_group":25389629,"tag_groups":[831077],"payee_inflected":[]},{"id":876953447,"user":41524,"account_income":2860424,"account_outcome":2860424,"date":"2023-12-10","income":"0.0000","outcome":"1330.0000","category":0,"payee":"","merchant":null,"comment":"\u041c\u043e\u043d\u0456\u0442\u043e\u0440\u0438","instrument_income":4,"instrument_outcome":4,"price":null,"created":"2023-12-10 10:46:27","changed":"2023-12-11 10:04:04.833326+03","deleted":false,"type_income":"ccard","type_outcome":"ccard","direction":-1,"inbalance_income":true,"inbalance_outcome":true,"hold":true,"tag_group":842559,"tag_groups":[34425689],"payee_inflected":[]},{"id":877444263,"user":41524,"account_income":12081809,"account_outcome":12081809,"date":"2023-12-09","income":"0.0000","outcome":"90.0000","category":0,"payee":"","merchant":null,"comment":"\u0421\u0442\u0440\u0438\u0436\u043a\u0430 \u0434\u0456\u0442\u0435\u0439","instrument_income":11303,"instrument_outcome":11303,"price":null,"created":"2023-12-11 10:02:10.792581","changed":"2023-12-11 10:02:10.792581+03","deleted":false,"type_income":"checking","type_outcome":"checking","direction":-1,"inbalance_income":true,"inbalance_outcome":true,"hold":null,"tag_group":25389629,"tag_groups":[25389629],"payee_inflected":[]},{"id":877443298,"user":41524,"account_income":2860400,"account_outcome":2860400,"date":"2023-12-09","income":"0.0000","outcome":"301.5500","category":0,"payee":"","merchant":null,"comment":"\u041d\u0435\u0442\u0444\u043b\u0456\u043a\u0441","instrument_income":4,"instrument_outcome":4,"price":null,"created":"2023-12-11 09:59:04.09615","changed":"2023-12-11 09:59:04.09615+03","deleted":false,"type_income":"ccard","type_outcome":"ccard","direction":-1,"inbalance_income":true,"inbalance_outcome":true,"hold":null,"tag_group":842534,"tag_groups":[756895],"payee_inflected":[]},{"id":876606536,"user":41524,"account_income":2860424,"account_outcome":2860424,"date":"2023-12-09","income":"0.0000","outcome":"2699.5300","category":0,"payee":"IKEA","merchant":2343020,"comment":"\u0415\u0442\u0430\u0436\u0435\u0440\u043a\u0430 \u0456 \u0434\u0440\u0456\u0431\u043d\u0438\u0446\u0456","instrument_income":4,"instrument_outcome":4,"price":null,"created":"2023-12-09 16:27:11","changed":"2023-12-11 10:04:28.11794+03","deleted":false,"type_income":"ccard","type_outcome":"ccard","direction":-1,"inbalance_income":true,"inbalance_outcome":true,"hold":false,"tag_group":31646942,"tag_groups":[34860310],"payee_inflected":[]},{"id":876577153,"user":41524,"account_income":2860424,"account_outcome":2860424,"date":"2023-12-09","income":"0.0000","outcome":"1288.8000","category":0,"payee":"Lidl","merchant":6090638,"comment":"","instrument_income":4,"instrument_outcome":4,"price":null,"created":"2023-12-09 15:31:42","changed":"2023-12-10 13:20:26.39568+03","deleted":false,"type_income":"ccard","type_outcome":"ccard","direction":-1,"inbalance_income":true,"inbalance_outcome":true,"hold":false,"tag_group":756886,"tag_groups":[756886],"payee_inflected":[]},{"id":877449036,"user":41524,"account_income":2860455,"account_outcome":2860455,"date":"2023-12-08","income":"5807.5200","outcome":"0.0000","category":0,"payee":"","merchant":null,"comment":"","instrument_income":1,"instrument_outcome":1,"price":null,"created":"2023-12-11 10:13:05.892611","changed":"2023-12-11 10:13:30.054525+03","deleted":false,"type_income":"checking","type_outcome":"checking","direction":1,"inbalance_income":false,"inbalance_outcome":false,"hold":false,"tag_group":756884,"tag_groups":[756884],"payee_inflected":[]},{"id":877443946,"user":41524,"account_income":12081809,"account_outcome":12081809,"date":"2023-12-08","income":"0.0000","outcome":"994.3000","category":0,"payee":"","merchant":null,"comment":"\u041e\u0440\u0435\u043d\u0434\u0430 \u043a\u043e\u043c\u0443\u043d\u0430\u043b\u044c\u043d\u0456","instrument_income":11303,"instrument_outcome":11303,"price":null,"created":"2023-12-11 10:01:16.2246","changed":"2023-12-11 10:01:16.2246+03","deleted":false,"type_income":"checking","type_outcome":"checking","direction":-1,"inbalance_income":true,"inbalance_outcome":true,"hold":null,"tag_group":842534,"tag_groups":[756895],"payee_inflected":[]},{"id":877443789,"user":41524,"account_income":12081809,"account_outcome":12081809,"date":"2023-12-08","income":"0.0000","outcome":"3800.0000","category":0,"payee":"","merchant":null,"comment":"\u041e\u0440\u0435\u043d\u0434\u0430","instrument_income":11303,"instrument_outcome":11303,"price":null,"created":"2023-12-11 10:00:40.961358","changed":"2023-12-11 10:00:40.961358+03","deleted":false,"type_income":"checking","type_outcome":"checking","direction":-1,"inbalance_income":true,"inbalance_outcome":true,"hold":null,"tag_group":842534,"tag_groups":[756895],"payee_inflected":[]},{"id":876235366,"user":41524,"account_income":2860424,"account_outcome":2860424,"date":"2023-12-08","income":"0.0000","outcome":"308.1800","category":0,"payee":"ZABKA Z7306 K.1","merchant":6177065,"comment":"","instrument_income":4,"instrument_outcome":4,"price":null,"created":"2023-12-08 19:58:42","changed":"2023-12-09 15:51:32.762654+03","deleted":false,"type_income":"ccard","type_outcome":"ccard","direction":-1,"inbalance_income":true,"inbalance_outcome":true,"hold":false,"tag_group":837707,"tag_groups":[26251072],"payee_inflected":[]},{"id":876224379,"user":41524,"account_income":2860424,"account_outcome":2860424,"date":"2023-12-08","income":"0.0000","outcome":"878.5200","category":0,"payee":"CARREFOUR","merchant":2343098,"comment":"","instrument_income":4,"instrument_outcome":4,"price":null,"created":"2023-12-08 19:18:54","changed":"2023-12-09 15:51:32.762654+03","deleted":false,"type_income":"ccard","type_outcome":"ccard","direction":-1,"inbalance_income":true,"inbalance_outcome":true,"hold":false,"tag_group":756886,"tag_groups":[756886],"payee_inflected":[]},{"id":879499852,"user":41524,"account_income":12199384,"account_outcome":12199384,"date":"2023-12-08","income":"0.0000","outcome":"200.0000","category":0,"payee":"","merchant":null,"comment":"","instrument_income":4,"instrument_outcome":4,"price":null,"created":"2023-12-08 18:47:15","changed":"2023-12-15 14:21:05.340523+03","deleted":false,"type_income":"ccard","type_outcome":"ccard","direction":-1,"inbalance_income":true,"inbalance_outcome":true,"hold":true,"tag_group":null,"tag_groups":null,"payee_inflected":[]},{"id":879499845,"user":41524,"account_income":12199384,"account_outcome":12199384,"date":"2023-12-08","income":"0.0000","outcome":"575.5900","category":0,"payee":"ZABKA ZB720 K.1","merchant":6141325,"comment":"","instrument_income":4,"instrument_outcome":4,"price":null,"created":"2023-12-08 17:37:45","changed":"2023-12-15 14:21:05.340523+03","deleted":false,"type_income":"ccard","type_outcome":"ccard","direction":-1,"inbalance_income":true,"inbalance_outcome":true,"hold":false,"tag_group":756886,"tag_groups":[756886],"payee_inflected":[]},{"id":879499844,"user":41524,"account_income":12199384,"account_outcome":12199384,"date":"2023-12-08","income":"0.0000","outcome":"560.2500","category":0,"payee":"GRAAL SP. Z O.O. 66163","merchant":null,"comment":"","instrument_income":4,"instrument_outcome":4,"price":null,"created":"2023-12-08 16:51:42","changed":"2023-12-15 14:21:05.340523+03","deleted":false,"type_income":"ccard","type_outcome":"ccard","direction":-1,"inbalance_income":true,"inbalance_outcome":true,"hold":false,"tag_group":756897,"tag_groups":[756897],"payee_inflected":[]},{"id":879499855,"user":41524,"account_income":12199384,"account_outcome":12199384,"date":"2023-12-08","income":"0.0000","outcome":"780.0000","category":0,"payee":"\u041a\u0432\u0430\u0440\u0442\u043f\u043b\u0430\u0442\u0430","merchant":2313705,"comment":"","instrument_income":4,"instrument_outcome":4,"price":null,"created":"2023-12-08 10:47:37","changed":"2023-12-15 14:21:05.340523+03","deleted":false,"type_income":"ccard","type_outcome":"ccard","direction":-1,"inbalance_income":true,"inbalance_outcome":true,"hold":true,"tag_group":842534,"tag_groups":[756895],"payee_inflected":[]},{"id":879499851,"user":41524,"account_income":12199384,"account_outcome":12199384,"date":"2023-12-08","income":"0.0000","outcome":"80.0000","category":0,"payee":"\u041e\u043f\u0435\u043d\u0441\u0432\u0456\u0442 (\u041f\u041f\u0424 \u0424\u0435\u043d\u0456\u043a\u0441 \u0412\u0422)","merchant":6195211,"comment":"","instrument_income":4,"instrument_outcome":4,"price":null,"created":"2023-12-08 10:47:15","changed":"2023-12-15 14:21:05.340523+03","deleted":false,"type_income":"ccard","type_outcome":"ccard","direction":-1,"inbalance_income":true,"inbalance_outcome":true,"hold":true,"tag_group":842534,"tag_groups":[756895],"payee_inflected":[]},{"id":879499857,"user":41524,"account_income":12199384,"account_outcome":12199384,"date":"2023-12-08","income":"0.0000","outcome":"233.1600","category":0,"payee":"\u0413\u0430\u0437 (\u0434\u043e\u0441\u0442\u0430\u0432\u043b\u0435\u043d\u043d\u044f)","merchant":2895607,"comment":"","instrument_income":4,"instrument_outcome":4,"price":null,"created":"2023-12-08 10:46:54","changed":"2023-12-15 14:21:05.340523+03","deleted":false,"type_income":"ccard","type_outcome":"ccard","direction":-1,"inbalance_income":true,"inbalance_outcome":true,"hold":true,"tag_group":842534,"tag_groups":[756895],"payee_inflected":[]},{"id":879499854,"user":41524,"account_income":12199384,"account_outcome":12199384,"date":"2023-12-08","income":"0.0000","outcome":"850.2800","category":0,"payee":"\u0413\u0430\u0437","merchant":2385003,"comment":"","instrument_income":4,"instrument_outcome":4,"price":null,"created":"2023-12-08 10:46:50","changed":"2023-12-15 14:21:05.340523+03","deleted":false,"type_income":"ccard","type_outcome":"ccard","direction":-1,"inbalance_income":true,"inbalance_outcome":true,"hold":true,"tag_group":842534,"tag_groups":[756895],"payee_inflected":[]},{"id":875946206,"user":41524,"account_income":2860424,"account_outcome":2860424,"date":"2023-12-08","income":"0.0000","outcome":"186.1200","category":0,"payee":"KOLEO bilety kolejowe","merchant":6107881,"comment":"","instrument_income":4,"instrument_outcome":4,"price":null,"created":"2023-12-08 10:20:13","changed":"2023-12-09 15:51:32.762654+03","deleted":false,"type_income":"ccard","type_outcome":"ccard","direction":-1,"inbalance_income":true,"inbalance_outcome":true,"hold":false,"tag_group":7033404,"tag_groups":[34999525],"payee_inflected":[]},{"id":879499846,"user":41524,"account_income":12199384,"account_outcome":12199384,"date":"2023-12-08","income":"454.0000","outcome":"0.0000","category":0,"payee":"FLIX,Karl-Liebknechtstr 29,Berlin,DE","merchant":null,"comment":"","instrument_income":4,"instrument_outcome":4,"price":null,"created":"2023-12-08 02:43:31","changed":"2023-12-15 14:21:05.340523+03","deleted":false,"type_income":"ccard","type_outcome":"ccard","direction":1,"inbalance_income":true,"inbalance_outcome":true,"hold":false,"tag_group":7033404,"tag_groups":[837708],"payee_inflected":[]},{"id":877443649,"user":41524,"account_income":12081809,"account_outcome":12081809,"date":"2023-12-07","income":"0.0000","outcome":"154.0000","category":0,"payee":"","merchant":null,"comment":"\u0417 \u043a\u0443\u0431\u0456\u043a\u043e\u043c","instrument_income":11303,"instrument_outcome":11303,"price":null,"created":"2023-12-11 10:00:20.544566","changed":"2023-12-11 10:00:20.544566+03","deleted":false,"type_income":"checking","type_outcome":"checking","direction":-1,"inbalance_income":true,"inbalance_outcome":true,"hold":null,"tag_group":837707,"tag_groups":[31707092],"payee_inflected":[]},{"id":877443160,"user":41524,"account_income":2860400,"account_outcome":2860400,"date":"2023-12-07","income":"0.0000","outcome":"1781.6700","category":0,"payee":"","merchant":null,"comment":"\u0421\u0430\u0434\u043e\u043a \u0445\u0430\u0440\u0447\u0443\u0432\u0430\u043d\u043d\u044f","instrument_income":4,"instrument_outcome":4,"price":null,"created":"2023-12-11 09:58:38.550877","changed":"2023-12-11 09:58:38.550877+03","deleted":false,"type_income":"ccard","type_outcome":"ccard","direction":-1,"inbalance_income":true,"inbalance_outcome":true,"hold":null,"tag_group":25389629,"tag_groups":[9117114],"payee_inflected":[]},{"id":877443106,"user":41524,"account_income":2860400,"account_outcome":2860400,"date":"2023-12-07","income":"0.0000","outcome":"8891.5900","category":0,"payee":"","merchant":null,"comment":"\u0421\u0430\u0434\u043e\u043a","instrument_income":4,"instrument_outcome":4,"price":null,"created":"2023-12-11 09:58:15.867348","changed":"2023-12-11 09:58:15.867348+03","deleted":false,"type_income":"ccard","type_outcome":"ccard","direction":-1,"inbalance_income":true,"inbalance_outcome":true,"hold":null,"tag_group":25389629,"tag_groups":[9117114],"payee_inflected":[]},{"id":875835235,"user":41524,"account_income":2860424,"account_outcome":2860424,"date":"2023-12-07","income":"0.0000","outcome":"138.7600","category":0,"payee":"PIJANA WISNIA","merchant":6090633,"comment":"","instrument_income":4,"instrument_outcome":4,"price":null,"created":"2023-12-08 00:38:29","changed":"2023-12-11 10:08:12.30422+03","deleted":false,"type_income":"ccard","type_outcome":"ccard","direction":-1,"inbalance_income":true,"inbalance_outcome":true,"hold":false,"tag_group":837707,"tag_groups":[31707092],"payee_inflected":[]},{"id":875820342,"user":41524,"account_income":12199384,"account_outcome":12199384,"date":"2023-12-07","income":"0.0000","outcome":"303.2500","category":0,"payee":"ZABKA ZB720 K.1","merchant":6141325,"comment":"","instrument_income":4,"instrument_outcome":4,"price":null,"created":"2023-12-07 18:29:25","changed":"2023-12-15 14:21:05.340523+03","deleted":false,"type_income":"ccard","type_outcome":"ccard","direction":-1,"inbalance_income":true,"inbalance_outcome":true,"hold":false,"tag_group":756886,"tag_groups":[756886],"payee_inflected":[]},{"id":875541864,"user":41524,"account_income":2860424,"account_outcome":2860424,"date":"2023-12-07","income":"0.0000","outcome":"308.0900","category":0,"payee":"ZABKA Z5771 K.1","merchant":null,"comment":"","instrument_income":4,"instrument_outcome":4,"price":null,"created":"2023-12-07 13:26:20","changed":"2023-12-08 19:41:13.870264+03","deleted":false,"type_income":"ccard","type_outcome":"ccard","direction":-1,"inbalance_income":true,"inbalance_outcome":true,"hold":false,"tag_group":837707,"tag_groups":[26251072],"payee_inflected":[]},{"id":875529371,"user":41524,"account_income":2860424,"account_outcome":2860424,"date":"2023-12-07","income":"0.0000","outcome":"466.9900","category":0,"payee":"Jakdojade","merchant":6090639,"comment":"","instrument_income":4,"instrument_outcome":4,"price":null,"created":"2023-12-07 12:49:17","changed":"2023-12-08 12:52:10.706712+03","deleted":false,"type_income":"ccard","type_outcome":"ccard","direction":-1,"inbalance_income":true,"inbalance_outcome":true,"hold":false,"tag_group":7033404,"tag_groups":[34999525],"payee_inflected":[]},{"id":875162813,"user":41524,"account_income":2860400,"account_outcome":2860455,"date":"2023-12-06","income":"109824.0700","outcome":"3000.0000","category":2,"payee":"","merchant":null,"comment":"","instrument_income":4,"instrument_outcome":1,"price":null,"created":"2023-12-06 18:04:30.669741","changed":"2023-12-06 18:04:30.669741+03","deleted":false,"type_income":"ccard","type_outcome":"checking","direction":0,"inbalance_income":true,"inbalance_outcome":false,"hold":null,"tag_group":null,"tag_groups":null,"payee_inflected":[]},{"id":875106907,"user":41524,"account_income":2860424,"account_outcome":2860424,"date":"2023-12-06","income":"0.0000","outcome":"229.3900","category":0,"payee":"KUCHNIA POLSKA JAGIENK","merchant":6147494,"comment":"","instrument_income":4,"instrument_outcome":4,"price":null,"created":"2023-12-06 16:00:12","changed":"2023-12-08 12:52:10.706712+03","deleted":false,"type_income":"ccard","type_outcome":"ccard","direction":-1,"inbalance_income":true,"inbalance_outcome":true,"hold":false,"tag_group":756886,"tag_groups":[7107248],"payee_inflected":[]},{"id":875021967,"user":41524,"account_income":12081809,"account_outcome":12081809,"date":"2023-12-06","income":"0.0000","outcome":"165.0000","category":0,"payee":"","merchant":null,"comment":"\u0421\u0442\u0440\u0430\u0445\u0443\u0432\u0430\u043d\u043d\u044f ","instrument_income":11303,"instrument_outcome":11303,"price":null,"created":"2023-12-06 13:56:16.53029","changed":"2023-12-06 13:56:16.53029+03","deleted":false,"type_income":"checking","type_outcome":"checking","direction":-1,"inbalance_income":true,"inbalance_outcome":true,"hold":null,"tag_group":842534,"tag_groups":[842534],"payee_inflected":[]},{"id":875348365,"user":41524,"account_income":12199384,"account_outcome":12199384,"date":"2023-12-06","income":"0.0000","outcome":"740.0000","category":0,"payee":"\u041a\u0430\u0440\u0456\u043d\u0430 \u0412.","merchant":null,"comment":"","instrument_income":4,"instrument_outcome":4,"price":null,"created":"2023-12-06 13:15:53","changed":"2023-12-07 00:34:38.423925+03","deleted":false,"type_income":"ccard","type_outcome":"ccard","direction":-1,"inbalance_income":true,"inbalance_outcome":true,"hold":true,"tag_group":842559,"tag_groups":[34425689],"payee_inflected":[]},{"id":874991621,"user":41524,"account_income":2860424,"account_outcome":2860424,"date":"2023-12-06","income":"0.0000","outcome":"3015.0800","category":0,"payee":"\u041c\u0430\u043c\u0430","merchant":2975161,"comment":"","instrument_income":4,"instrument_outcome":4,"price":null,"created":"2023-12-06 12:37:32","changed":"2023-12-06 12:50:52.663531+03","deleted":false,"type_income":"ccard","type_outcome":"ccard","direction":-1,"inbalance_income":true,"inbalance_outcome":true,"hold":true,"tag_group":1409781,"tag_groups":[1409781],"payee_inflected":[]},{"id":874961582,"user":41524,"account_income":12081809,"account_outcome":2860400,"date":"2023-12-06","income":"2500.0000","outcome":"23375.0000","category":2,"payee":"","merchant":null,"comment":"","instrument_income":11303,"instrument_outcome":4,"price":null,"created":"2023-12-06 11:57:12","changed":"2023-12-06 11:57:20.900805+03","deleted":false,"type_income":"checking","type_outcome":"ccard","direction":0,"inbalance_income":true,"inbalance_outcome":true,"hold":null,"tag_group":null,"tag_groups":null,"payee_inflected":[]},{"id":874687680,"user":41524,"account_income":2860424,"account_outcome":2860424,"date":"2023-12-05","income":"0.0000","outcome":"141.7400","category":0,"payee":"CARREFOUR","merchant":2343098,"comment":"","instrument_income":4,"instrument_outcome":4,"price":null,"created":"2023-12-05 20:01:16","changed":"2023-12-06 16:18:11.27119+03","deleted":false,"type_income":"ccard","type_outcome":"ccard","direction":-1,"inbalance_income":true,"inbalance_outcome":true,"hold":false,"tag_group":756886,"tag_groups":[756886],"payee_inflected":[]},{"id":874942755,"user":41524,"account_income":12199384,"account_outcome":12199384,"date":"2023-12-05","income":"0.0000","outcome":"691.5300","category":0,"payee":"Lidl","merchant":6090638,"comment":"","instrument_income":4,"instrument_outcome":4,"price":null,"created":"2023-12-05 17:42:43","changed":"2023-12-07 00:34:38.423925+03","deleted":false,"type_income":"ccard","type_outcome":"ccard","direction":-1,"inbalance_income":true,"inbalance_outcome":true,"hold":false,"tag_group":756886,"tag_groups":[756886],"payee_inflected":[]},{"id":874942756,"user":41524,"account_income":12199384,"account_outcome":12199384,"date":"2023-12-05","income":"0.0000","outcome":"140.9900","category":0,"payee":"IKEA","merchant":2343020,"comment":"","instrument_income":4,"instrument_outcome":4,"price":null,"created":"2023-12-05 16:55:28","changed":"2023-12-07 00:34:38.423925+03","deleted":false,"type_income":"ccard","type_outcome":"ccard","direction":-1,"inbalance_income":true,"inbalance_outcome":true,"hold":false,"tag_group":31646942,"tag_groups":[34860310],"payee_inflected":[]},{"id":874566024,"user":41524,"account_income":2860424,"account_outcome":2860424,"date":"2023-12-05","income":"0.0000","outcome":"281.9800","category":0,"payee":"BEER HOUSE PUB RESTO","merchant":2343100,"comment":"","instrument_income":4,"instrument_outcome":4,"price":null,"created":"2023-12-05 16:14:50","changed":"2023-12-06 14:02:54.740176+03","deleted":false,"type_income":"ccard","type_outcome":"ccard","direction":-1,"inbalance_income":true,"inbalance_outcome":true,"hold":false,"tag_group":756886,"tag_groups":[7107248],"payee_inflected":[]},{"id":874942758,"user":41524,"account_income":12199384,"account_outcome":12199384,"date":"2023-12-05","income":"0.0000","outcome":"1399.8500","category":0,"payee":"Zara","merchant":6213724,"comment":"","instrument_income":4,"instrument_outcome":4,"price":null,"created":"2023-12-05 14:57:24","changed":"2023-12-07 00:34:38.423925+03","deleted":false,"type_income":"ccard","type_outcome":"ccard","direction":-1,"inbalance_income":true,"inbalance_outcome":true,"hold":false,"tag_group":756897,"tag_groups":[756897],"payee_inflected":[]},{"id":874412253,"user":41524,"account_income":2860424,"account_outcome":2860424,"date":"2023-12-05","income":"0.0000","outcome":"422.6000","category":0,"payee":"ZABKA Z5771 K.1","merchant":null,"comment":"","instrument_income":4,"instrument_outcome":4,"price":null,"created":"2023-12-05 12:23:37","changed":"2023-12-06 12:50:52.663531+03","deleted":false,"type_income":"ccard","type_outcome":"ccard","direction":-1,"inbalance_income":true,"inbalance_outcome":true,"hold":false,"tag_group":837707,"tag_groups":[26251072],"payee_inflected":[]},{"id":874357987,"user":41524,"account_income":2860424,"account_outcome":2860424,"date":"2023-12-05","income":"0.0000","outcome":"374.8600","category":0,"payee":"Allegro","merchant":6141326,"comment":"\u0421\u043c\u0430\u0440\u0442 \u043f\u0456\u0434\u043f\u0438\u0441\u043a\u0430","instrument_income":4,"instrument_outcome":4,"price":null,"created":"2023-12-05 10:50:16","changed":"2023-12-11 10:15:49.0793+03","deleted":false,"type_income":"ccard","type_outcome":"ccard","direction":-1,"inbalance_income":true,"inbalance_outcome":true,"hold":false,"tag_group":842559,"tag_groups":[842559],"payee_inflected":[]},{"id":873985774,"user":41524,"account_income":2860424,"account_outcome":2860424,"date":"2023-12-04","income":"0.0000","outcome":"150.3200","category":0,"payee":"BAR SMAK","merchant":6213720,"comment":"","instrument_income":4,"instrument_outcome":4,"price":null,"created":"2023-12-04 15:32:35","changed":"2023-12-05 16:29:00.961605+03","deleted":false,"type_income":"ccard","type_outcome":"ccard","direction":-1,"inbalance_income":true,"inbalance_outcome":true,"hold":false,"tag_group":756886,"tag_groups":[7107248],"payee_inflected":[]},{"id":873887750,"user":41524,"account_income":2860424,"account_outcome":2860424,"date":"2023-12-04","income":"166.0600","outcome":"0.0000","category":0,"payee":"","merchant":null,"comment":"\u0412\u0438\u0432\u0435\u0434\u0435\u043d\u043d\u044f \u043a\u0435\u0448\u0431\u0435\u043a\u0443 206.30\u20b4","instrument_income":4,"instrument_outcome":4,"price":null,"created":"2023-12-04 12:26:33","changed":"2023-12-04 12:27:04.625597+03","deleted":false,"type_income":"ccard","type_outcome":"ccard","direction":1,"inbalance_income":true,"inbalance_outcome":true,"hold":false,"tag_group":756884,"tag_groups":[756893],"payee_inflected":[]},{"id":873880029,"user":41524,"account_income":2860424,"account_outcome":2860424,"date":"2023-12-04","income":"0.0000","outcome":"149.0000","category":0,"payee":"YouTube","merchant":null,"comment":"","instrument_income":4,"instrument_outcome":4,"price":null,"created":"2023-12-04 11:56:53","changed":"2023-12-05 11:14:51.097945+03","deleted":false,"type_income":"ccard","type_outcome":"ccard","direction":-1,"inbalance_income":true,"inbalance_outcome":true,"hold":false,"tag_group":842534,"tag_groups":[756895],"payee_inflected":[]},{"id":873808769,"user":41524,"account_income":2860424,"account_outcome":2860424,"date":"2023-12-04","income":"0.0000","outcome":"300.0000","category":0,"payee":"\u041c\u0430\u043a\u0441\u0438\u043c","merchant":4630495,"comment":"","instrument_income":4,"instrument_outcome":4,"price":null,"created":"2023-12-04 10:01:27","changed":"2023-12-04 10:21:05.463573+03","deleted":false,"type_income":"ccard","type_outcome":"ccard","direction":-1,"inbalance_income":true,"inbalance_outcome":true,"hold":true,"tag_group":25389629,"tag_groups":[831077],"payee_inflected":[]},{"id":874942759,"user":41524,"account_income":12199384,"account_outcome":12199384,"date":"2023-12-03","income":"0.0000","outcome":"199.0000","category":0,"payee":"PlayStation Network","merchant":6219183,"comment":"","instrument_income":4,"instrument_outcome":4,"price":null,"created":"2023-12-04 01:03:50","changed":"2023-12-06 11:04:37.164566+03","deleted":false,"type_income":"ccard","type_outcome":"ccard","direction":-1,"inbalance_income":true,"inbalance_outcome":true,"hold":false,"tag_group":25389629,"tag_groups":[831077],"payee_inflected":[]},{"id":873890547,"user":41524,"account_income":2860424,"account_outcome":2860424,"date":"2023-12-03","income":"0.0000","outcome":"450.0000","category":0,"payee":"ZABKA Z8090 K.3","merchant":null,"comment":"","instrument_income":4,"instrument_outcome":4,"price":null,"created":"2023-12-03 19:45:03","changed":"2023-12-04 12:31:46.237387+03","deleted":false,"type_income":"ccard","type_outcome":"ccard","direction":-1,"inbalance_income":true,"inbalance_outcome":true,"hold":null,"tag_group":837707,"tag_groups":[26251072],"payee_inflected":[]},{"id":873890546,"user":41524,"account_income":2860424,"account_outcome":2860424,"date":"2023-12-03","income":"0.0000","outcome":"544.0300","category":0,"payee":"ZABKA Z8090 K.3","merchant":6213756,"comment":"","instrument_income":4,"instrument_outcome":4,"price":null,"created":"2023-12-03 19:45:02","changed":"2023-12-04 12:31:46.237387+03","deleted":false,"type_income":"ccard","type_outcome":"ccard","direction":-1,"inbalance_income":true,"inbalance_outcome":true,"hold":false,"tag_group":837707,"tag_groups":[31707092],"payee_inflected":[]},{"id":874942757,"user":41524,"account_income":12199384,"account_outcome":12199384,"date":"2023-12-03","income":"0.0000","outcome":"469.6000","category":0,"payee":"Jakdojade","merchant":6090639,"comment":"","instrument_income":4,"instrument_outcome":4,"price":null,"created":"2023-12-03 19:05:59","changed":"2023-12-06 11:04:37.164566+03","deleted":false,"type_income":"ccard","type_outcome":"ccard","direction":-1,"inbalance_income":true,"inbalance_outcome":true,"hold":false,"tag_group":7033404,"tag_groups":[34999525],"payee_inflected":[]},{"id":873312738,"user":41524,"account_income":2860424,"account_outcome":2860424,"date":"2023-12-03","income":"0.0000","outcome":"1323.7600","category":0,"payee":"PP *sensu.pl","merchant":6213713,"comment":"","instrument_income":4,"instrument_outcome":4,"price":null,"created":"2023-12-03 11:21:19","changed":"2023-12-04 15:47:45.672685+03","deleted":false,"type_income":"ccard","type_outcome":"ccard","direction":-1,"inbalance_income":true,"inbalance_outcome":true,"hold":false,"tag_group":842559,"tag_groups":[756890],"payee_inflected":[]},{"id":873376271,"user":41524,"account_income":12199384,"account_outcome":12199384,"date":"2023-12-03","income":"0.0000","outcome":"215.9600","category":0,"payee":"BONITO.PL","merchant":6213757,"comment":"\u041a\u0440\u0438\u043b\u0430","instrument_income":4,"instrument_outcome":4,"price":null,"created":"2023-12-03 02:06:26","changed":"2023-12-06 11:04:37.164566+03","deleted":false,"type_income":"ccard","type_outcome":"ccard","direction":-1,"inbalance_income":true,"inbalance_outcome":true,"hold":false,"tag_group":25389629,"tag_groups":[9117114],"payee_inflected":[]},{"id":874959109,"user":41524,"account_income":2860400,"account_outcome":2860400,"date":"2023-12-02","income":"0.0000","outcome":"1131.3300","category":0,"payee":"","merchant":null,"comment":"\u0411\u0430\u0440\u0431\u0435\u0440","instrument_income":4,"instrument_outcome":4,"price":null,"created":"2023-12-06 11:50:58","changed":"2023-12-06 13:08:29.083878+03","deleted":false,"type_income":"ccard","type_outcome":"ccard","direction":-1,"inbalance_income":true,"inbalance_outcome":true,"hold":false,"tag_group":858355,"tag_groups":[35282059],"payee_inflected":[]},{"id":873884355,"user":41524,"account_income":2860400,"account_outcome":2860400,"date":"2023-12-02","income":"0.0000","outcome":"11414.6800","category":0,"payee":"","merchant":null,"comment":"Auchan","instrument_income":4,"instrument_outcome":4,"price":null,"created":"2023-12-04 12:18:41.42568","changed":"2023-12-06 13:08:18.114757+03","deleted":false,"type_income":"ccard","type_outcome":"ccard","direction":-1,"inbalance_income":true,"inbalance_outcome":true,"hold":false,"tag_group":756886,"tag_groups":[756886],"payee_inflected":[]},{"id":873118566,"user":41524,"account_income":2860424,"account_outcome":2860424,"date":"2023-12-02","income":"0.0000","outcome":"157.4000","category":0,"payee":"\u0410\u0448\u0430\u043d","merchant":5096016,"comment":"","instrument_income":4,"instrument_outcome":4,"price":null,"created":"2023-12-02 21:14:46","changed":"2023-12-03 20:06:22.363821+03","deleted":false,"type_income":"ccard","type_outcome":"ccard","direction":-1,"inbalance_income":true,"inbalance_outcome":true,"hold":false,"tag_group":756886,"tag_groups":[756886],"payee_inflected":[]},{"id":873050374,"user":41524,"account_income":2860424,"account_outcome":2860424,"date":"2023-12-02","income":"0.0000","outcome":"384.9300","category":0,"payee":"JYSK","merchant":6219231,"comment":"\u0413\u043d\u043e\u043c \u0456 \u0432\u0430\u0437\u0430","instrument_income":4,"instrument_outcome":4,"price":null,"created":"2023-12-02 18:21:07","changed":"2023-12-06 13:40:30.477806+03","deleted":false,"type_income":"ccard","type_outcome":"ccard","direction":-1,"inbalance_income":true,"inbalance_outcome":true,"hold":false,"tag_group":31646942,"tag_groups":[34860310],"payee_inflected":[]},{"id":872970914,"user":41524,"account_income":2860424,"account_outcome":2860424,"date":"2023-12-02","income":"0.0000","outcome":"281.6100","category":0,"payee":"Jakdojade","merchant":6090639,"comment":"\u041c\u0430\u043a\u0441\u0443","instrument_income":4,"instrument_outcome":4,"price":null,"created":"2023-12-02 16:14:17","changed":"2023-12-04 12:22:34.991192+03","deleted":false,"type_income":"ccard","type_outcome":"ccard","direction":-1,"inbalance_income":true,"inbalance_outcome":true,"hold":false,"tag_group":25389629,"tag_groups":[831077],"payee_inflected":[]},{"id":872777683,"user":41524,"account_income":2860424,"account_outcome":2860424,"date":"2023-12-02","income":"0.0000","outcome":"1399.4800","category":0,"payee":"PIJANA WISNIA","merchant":6090633,"comment":"","instrument_income":4,"instrument_outcome":4,"price":null,"created":"2023-12-02 02:27:39","changed":"2023-12-03 11:40:35.512254+03","deleted":false,"type_income":"ccard","type_outcome":"ccard","direction":-1,"inbalance_income":true,"inbalance_outcome":true,"hold":false,"tag_group":837707,"tag_groups":[31707092],"payee_inflected":[]},{"id":872680951,"user":41524,"account_income":2860424,"account_outcome":2860424,"date":"2023-12-01","income":"0.0000","outcome":"328.6100","category":0,"payee":"BEER STREET","merchant":6090634,"comment":"","instrument_income":4,"instrument_outcome":4,"price":null,"created":"2023-12-02 00:03:57","changed":"2023-12-02 16:20:50.044007+03","deleted":false,"type_income":"ccard","type_outcome":"ccard","direction":-1,"inbalance_income":true,"inbalance_outcome":true,"hold":false,"tag_group":837707,"tag_groups":[31707092],"payee_inflected":[]},{"id":872668006,"user":41524,"account_income":2860424,"account_outcome":2860424,"date":"2023-12-01","income":"0.0000","outcome":"300.6300","category":0,"payee":"OGIEN BAR COFFEE","merchant":null,"comment":"","instrument_income":4,"instrument_outcome":4,"price":null,"created":"2023-12-01 23:21:47","changed":"2023-12-03 11:40:35.512254+03","deleted":false,"type_income":"ccard","type_outcome":"ccard","direction":-1,"inbalance_income":true,"inbalance_outcome":true,"hold":false,"tag_group":837707,"tag_groups":[33078367],"payee_inflected":[]},{"id":872660833,"user":41524,"account_income":2860424,"account_outcome":2860424,"date":"2023-12-01","income":"0.0000","outcome":"1267.8100","category":0,"payee":"GRECKA TAWERNA MINOAS","merchant":null,"comment":"","instrument_income":4,"instrument_outcome":4,"price":null,"created":"2023-12-01 23:10:39","changed":"2023-12-02 16:20:50.044007+03","deleted":false,"type_income":"ccard","type_outcome":"ccard","direction":-1,"inbalance_income":true,"inbalance_outcome":true,"hold":false,"tag_group":837707,"tag_groups":[33078367],"payee_inflected":[]},{"id":872610887,"user":41524,"account_income":2860424,"account_outcome":2860424,"date":"2023-12-01","income":"0.0000","outcome":"281.9800","category":0,"payee":"CERASUS SP. Z O.O. SP.","merchant":6159617,"comment":"","instrument_income":4,"instrument_outcome":4,"price":null,"created":"2023-12-01 21:12:32","changed":"2023-12-03 11:40:35.512254+03","deleted":false,"type_income":"ccard","type_outcome":"ccard","direction":-1,"inbalance_income":true,"inbalance_outcome":true,"hold":false,"tag_group":837707,"tag_groups":[33078367],"payee_inflected":[]},{"id":872597057,"user":41524,"account_income":2860424,"account_outcome":2860424,"date":"2023-12-01","income":"0.0000","outcome":"472.9600","category":0,"payee":"Jakdojade","merchant":6090639,"comment":"","instrument_income":4,"instrument_outcome":4,"price":null,"created":"2023-12-01 20:50:37","changed":"2023-12-02 16:20:50.044007+03","deleted":false,"type_income":"ccard","type_outcome":"ccard","direction":-1,"inbalance_income":true,"inbalance_outcome":true,"hold":false,"tag_group":7033404,"tag_groups":[34999525],"payee_inflected":[]},{"id":873376270,"user":41524,"account_income":12199384,"account_outcome":12199384,"date":"2023-12-01","income":"0.0000","outcome":"854.0000","category":0,"payee":"FLIX","merchant":6213718,"comment":"","instrument_income":4,"instrument_outcome":4,"price":null,"created":"2023-12-01 19:26:26","changed":"2023-12-03 13:54:52.576832+03","deleted":false,"type_income":"ccard","type_outcome":"ccard","direction":-1,"inbalance_income":true,"inbalance_outcome":true,"hold":false,"tag_group":7033404,"tag_groups":[7033404],"payee_inflected":[]},{"id":872405265,"user":41524,"account_income":2860424,"account_outcome":2860424,"date":"2023-12-01","income":"0.0000","outcome":"264.8300","category":0,"payee":"KUCHNIA POLSKA JAGIENK","merchant":6147494,"comment":"","instrument_income":4,"instrument_outcome":4,"price":null,"created":"2023-12-01 15:30:30","changed":"2023-12-02 13:10:01.971672+03","deleted":false,"type_income":"ccard","type_outcome":"ccard","direction":-1,"inbalance_income":true,"inbalance_outcome":true,"hold":false,"tag_group":756886,"tag_groups":[7107248],"payee_inflected":[]},{"id":872278073,"user":41524,"account_income":2860424,"account_outcome":2860424,"date":"2023-12-01","income":"0.0000","outcome":"175.0000","category":0,"payee":"Vodafone\n+380997866643","merchant":4630494,"comment":"","instrument_income":4,"instrument_outcome":4,"price":null,"created":"2023-12-01 11:49:57","changed":"2023-12-01 11:57:53.21836+03","deleted":false,"type_income":"ccard","type_outcome":"ccard","direction":-1,"inbalance_income":true,"inbalance_outcome":true,"hold":true,"tag_group":25389629,"tag_groups":[831077],"payee_inflected":[]},{"id":873376265,"user":41524,"account_income":12199384,"account_outcome":12199384,"date":"2023-12-01","income":"0.0000","outcome":"155.9100","category":0,"payee":"ZABKA ZB720 K.1","merchant":6141325,"comment":"","instrument_income":4,"instrument_outcome":4,"price":null,"created":"2023-12-01 10:24:00","changed":"2023-12-03 13:54:52.576832+03","deleted":false,"type_income":"ccard","type_outcome":"ccard","direction":-1,"inbalance_income":true,"inbalance_outcome":true,"hold":false,"tag_group":756886,"tag_groups":[756886],"payee_inflected":[]}]